fast_registry/__init__.py
fast_registry/exceptions.py
fast_registry/registry.py
fast_registry/validators.py
fast_registry-0.2.1.dist-info/LICENSE
fast_registry-0.2.1.dist-info/WHEEL
fast_registry-0.2.1.dist-info/METADATA
fast_registry-0.2.1.dist-info/RECORD
