Metadata-Version: 2.1
Name: fast-registry
Version: 0.2.1
Summary: Everything you need to implement maintainable and easy to use registry patterns in your project.
Home-page: https://github.com/danialkeimasi/python-fast-registry
License: MIT
Author: Danial Keimasi
Author-email: danialkeimasi@gmail.com
Requires-Python: >=3.6,<4.0
Classifier: License :: OSI Approved :: MIT License
Classifier: Programming Language :: Python :: 3
Classifier: Programming Language :: Python :: 3.10
Classifier: Programming Language :: Python :: 3.6
Classifier: Programming Language :: Python :: 3.7
Classifier: Programming Language :: Python :: 3.8
Classifier: Programming Language :: Python :: 3.9
Classifier: Topic :: Software Development :: Build Tools
Classifier: Topic :: Software Development :: Libraries :: Python Modules
Project-URL: Bug Tracker, https://github.com/danialkeimasi/python-fast-registry/issues
